CHANGES.rst
LICENSE
MANIFEST.in
README.rst
VERSION
requirements.txt
setup.cfg
setup.py
unicore/__init__.py
unicore/__init__.pyc
unicore.distribute.egg-info/PKG-INFO
unicore.distribute.egg-info/SOURCES.txt
unicore.distribute.egg-info/dependency_links.txt
unicore.distribute.egg-info/entry_points.txt
unicore.distribute.egg-info/namespace_packages.txt
unicore.distribute.egg-info/not-zip-safe
unicore.distribute.egg-info/requires.txt
unicore.distribute.egg-info/top_level.txt
unicore/distribute/__init__.py
unicore/distribute/__init__.pyc
unicore/distribute/events.py
unicore/distribute/events.pyc
unicore/distribute/scripts.py
unicore/distribute/scripts.pyc
unicore/distribute/tasks.py
unicore/distribute/tasks.pyc
unicore/distribute/utils.py
unicore/distribute/utils.pyc
unicore/distribute/alembic/README
unicore/distribute/alembic/env.py
unicore/distribute/alembic/script.py.mako
unicore/distribute/alembic/versions/5ade3d942429_.py
unicore/distribute/api/__init__.py
unicore/distribute/api/__init__.pyc
unicore/distribute/api/proxy.py
unicore/distribute/api/proxy.pyc
unicore/distribute/api/repo_status.py
unicore/distribute/api/repo_status.pyc
unicore/distribute/api/repos.py
unicore/distribute/api/repos.pyc
unicore/distribute/api/validators.py
unicore/distribute/api/validators.pyc
unicore/distribute/api/tests/__init__.py
unicore/distribute/api/tests/__init__.pyc
unicore/distribute/api/tests/test_repo_status.py
unicore/distribute/api/tests/test_repos.py
unicore/distribute/api/tests/test_tasks.py
unicore/distribute/api/tests/test_utils.py
unicore/distribute/api/tests/test_validators.py
unicore/distribute/api/tests/__pycache__/test_repo_status.cpython-27-PYTEST.pyc
unicore/distribute/api/tests/__pycache__/test_repos.cpython-27-PYTEST.pyc
unicore/distribute/api/tests/__pycache__/test_tasks.cpython-27-PYTEST.pyc
unicore/distribute/api/tests/__pycache__/test_utils.cpython-27-PYTEST.pyc
unicore/distribute/api/tests/__pycache__/test_validators.cpython-27-PYTEST.pyc
unicore/distribute/tests/__init__.py
unicore/distribute/tests/__init__.pyc
unicore/distribute/tests/base.py
unicore/distribute/tests/base.pyc
unicore/distribute/tests/test_events.py
unicore/distribute/tests/test_proxy.py
unicore/distribute/tests/test_scripts.py
unicore/distribute/tests/__pycache__/test_events.cpython-27-PYTEST.pyc
